dcl_stats_n_plots/__init__.py
dcl_stats_n_plots/_modidx.py
dcl_stats_n_plots/_nbdev.py
dcl_stats_n_plots/annotations.py
dcl_stats_n_plots/dashboards.py
dcl_stats_n_plots/database.py
dcl_stats_n_plots/downloads.py
dcl_stats_n_plots/gui.py
dcl_stats_n_plots/gui_refactored.py
dcl_stats_n_plots/gui_tutorial.py
dcl_stats_n_plots/main.py
dcl_stats_n_plots/main_refactored.py
dcl_stats_n_plots/plots.py
dcl_stats_n_plots/plots_refactored.py
dcl_stats_n_plots/stats.py
dcl_stats_n_plots/stats_refactored.py
dcl_stats_n_plots-0.4.0.dist-info/LICENSE
dcl_stats_n_plots-0.4.0.dist-info/METADATA
dcl_stats_n_plots-0.4.0.dist-info/WHEEL
dcl_stats_n_plots-0.4.0.dist-info/entry_points.txt
dcl_stats_n_plots-0.4.0.dist-info/top_level.txt
dcl_stats_n_plots-0.4.0.dist-info/RECORD
