Metadata-Version: 2.1
Name: dcl-stats-n-plots
Version: 0.4.0
Summary: coming soon
Home-page: https://github.com/DSegebarth/dcl_stats_n_plots/tree/master/
Author: Dennis Segebarth
Author-email: segebarth_d@ukw.de
License: Apache Software License 2.0
Keywords: DCLwidgets
Classifier: Development Status :: 4 - Beta
Classifier: Intended Audience :: Developers
Classifier: Natural Language :: English
Classifier: Programming Language :: Python :: 3.9
Classifier: Programming Language :: Python :: 3.10
Classifier: License :: OSI Approved :: Apache Software License
Requires-Python: >=3.9
License-File: LICENSE
Requires-Dist: ipywidgets
Requires-Dist: matplotlib (>=3.3.4)
Requires-Dist: pingouin (>=0.3.12)
Requires-Dist: seaborn (==0.11.2)
Requires-Dist: xlrd (>=1.2.0)
Requires-Dist: openpyxl (>=3.0.0)
Provides-Extra: dev
